processador/ALU.v
module ALU(
    input wire [31:0] A,           // Operando 1
    input wire [31:0] B,           // Operando 2
    input wire [3:0] ALUOperation, // Código da operação ALU
    output reg [31:0] ALUResult,   // Resultado da ALU
    output wire Zero               // Sinal Zero (ativo quando ALUResult é 0)
);

    // Define o comportamento da ALU
    always @(*) begin
        case (ALUOperation)
            4'b1011: ALUResult = A & B;          // opcode 0x0B -> AND
            4'b1100: ALUResult = A | B;          // opcode 0x0C -> OR
            4'b1001: ALUResult = A + B;          // opcode 0x09 -> Soma
            4'b1010: ALUResult = A - B;          // opcode 0x0A -> Subtração
            default: ALUResult = 32'b0;          // Operação inválida
        endcase
    end

    // Define o sinal Zero
    assign Zero = (ALUResult == 32'b0) ? 1'b1 : 1'b0;

endmodule

processador/ShiftLeft2.v
module ShiftLeft2(
    input [15:0] in, 
    output [31:0] out
);

    assign out = {14'b0, in << 2};

endmodule

processador/ALUControl.v
module ALUControl(
    input [1:0] i_ALUOp,
    output reg [3:0] o_Op
);

    always@(*) begin
        case (i_ALUOp)
            2'b00: begin
                o_Op = 4'b1011;
            end
            2'b01: begin
                o_Op = 4'b1100;
            end
            2'b10: begin
                o_Op = 4'b1001;
            end
            2'b11: begin
                o_Op = 4'b1010;
            end
            default: begin
                o_Op = 4'b0000;
            end
        endcase
    end

endmodule

processador/ControlLogicUnit.v
module ControlLogicUnit(
    input [7:0] Opcode,
    output reg Jump,
    output reg MemRead,
    output reg [1:0] ALUOp,
    output reg MemWrite,
    output reg ALUSrc,
    output reg RegWrite,
    output reg RegToReg,
    output reg Halt

);

    always@(*) begin
        case (Opcode)
            8'h00: begin // mov imm
                Jump     = 0;
                MemRead  = 0;
                ALUOp    = 2'b10;
                MemWrite = 0;
                ALUSrc   = 1;
                RegWrite = 1;
                RegToReg = 1;
                Halt     = 0;
                end
            8'h01: begin // mov reg
                Jump     = 0;
                MemRead  = 0;
                ALUOp    = 2'b10;
                MemWrite = 0;
                ALUSrc   = 0;
                RegWrite = 1;
                RegToReg = 1;
                Halt     = 0;
                end
            8'h02: begin // mov from mem
                Jump     = 0;
                MemRead  = 1;
                ALUOp    = 2'b10;
                MemWrite = 0;
                ALUSrc   = 0;
                RegWrite = 1;
                RegToReg = 0;
                Halt     = 0;
                end
            8'h03: begin // mov to mem
                Jump     = 0;
                MemRead  = 0;
                ALUOp    = 2'b00;
                MemWrite = 1;
                ALUSrc   = 0;
                RegWrite = 0;
                RegToReg = 0;
                Halt     = 0;
                end
            8'h05: begin // jmp
                Jump     = 1;
                MemRead  = 0;
                ALUOp    = 10;
                MemWrite = 0;
                ALUSrc   = 1;
                RegWrite = 0;
                RegToReg = 0;
                Halt     = 0;
                end
            8'h09: begin // add
                Jump     = 0;
                MemRead  = 0;
                ALUOp    = 2'b10;
                MemWrite = 0;
                ALUSrc   = 0;
                RegWrite = 1;
                RegToReg = 0;
                Halt     = 0;
                end
            8'h0A: begin // sub
                Jump     = 0;
                MemRead  = 0;
                ALUOp    = 2'b11;
                MemWrite = 0;
                ALUSrc   = 0;
                RegWrite = 1;
                RegToReg = 0;
                Halt     = 0;
                end
            8'h0B: begin // and
                Jump     = 0;
                MemRead  = 0;
                ALUOp    = 2'b00;
                MemWrite = 0;
                ALUSrc   = 0;
                RegWrite = 1;
                RegToReg = 0;
                Halt     = 0;
                end
            8'h0C: begin // or
                Jump     = 0;
                MemRead  = 0;
                ALUOp    = 2'b01;
                MemWrite = 0;
                ALUSrc   = 0;
                RegWrite = 1;
                RegToReg = 0;
                Halt     = 0;
                end
            8'hFF: begin // halt
                Jump     = 0;
                MemRead  = 0;
                ALUOp    = 2'b00;
                MemWrite = 0;
                ALUSrc   = 0;
                RegWrite = 0;
                RegToReg = 0;
                Halt     = 1;
                end
            default: begin
                Jump     = 0;
                MemRead  = 0;
                ALUOp    = 00;
                MemWrite = 0;
                ALUSrc   = 0;
                RegWrite = 0;
                RegToReg = 0;
                Halt     = 0;
            end
        endcase
    end

endmodule

processador/Registradores.v
module Registradores(
    input wire [3:0] ReadRegister1,  // Endereço do registrador para leitura 1
    input wire [3:0] ReadRegister2,  // Endereço do registrador para leitura 2
    input wire [3:0] WriteRegister,  // Endereço do registrador para escrita
    input wire [31:0] WriteData,     // Dados a serem escritos
    input wire RegWrite,             // Habilitação de escrita
    input wire clock,                // sincronizar com o clock do sistema
    output wire [31:0] ReadData1,    // Dados lidos do registrador 1
    output wire [31:0] ReadData2     // Dados lidos do registrador 2
);

    // Banco de registradores: 16 registradores de 32 bits
    reg [31:0] registers [15:0];

    // Inicialização dos registradores (opcional, apenas para simulação)
    integer i;
    initial begin
        for (i = 0; i < 16; i = i + 1) begin
            registers[i] = 32'b0;  // Inicializa todos com zero
        end
    end

    // Leitura combinacional
    assign ReadData1 = registers[ReadRegister1];
    assign ReadData2 = registers[ReadRegister2];

    // Escrita síncrona
    always @(posedge clock) begin
        if (RegWrite && WriteRegister != 4'b0) begin
            registers[WriteRegister] <= WriteData;  // Escreve no registrador
        end
    end

endmodule

processador/extensao_sinal.v
module extensao_sinal(
  input wire [15:0] in,    // Entrada de 16 bits a ser estendida
  output wire [31:0] out   // Saída de 32 bits com sinal estendido
);
  assign out = {{16{in[15]}}, in};

endmodule

processador/memoria.v
module memory (
    input wire clk,
    input wire MemWrite,  // 1 para escrever
    input wire MemRead,   // 1 para ler
    input wire [31:0] instructionAddress,
    input wire [31:0] MemAddress,
    input wire [31:0] WriteData,
    output reg [31:0] ReadData,
    output wire [31:0] instruction

);

    reg [31:0] mem_array [0:63]; // reg pra permitir a escrita no array, 64 bytes por palavra

    wire [5:0] word_index = MemAddress[7:2]; // 6 bits para indexar 64 palavras

    assign instruction = mem_array[instructionAddress[7:2]];

    integer i;
    initial begin
        mem_array[0] = 32'h00100040;
        mem_array[1] = 32'h01210000;
        mem_array[2] = 32'h03210000;
        mem_array[3] = 32'h02320000;
        mem_array[4] = 32'h05000003;
        mem_array[5] = 32'h004000FF;
        mem_array[6] = 32'h004000FF;
        mem_array[7] = 32'h004000FF;
        mem_array[8] = 32'h09120000;
        mem_array[9] = 32'h0A120000;
        mem_array[10] = 32'h0B140000;
        mem_array[11] = 32'h0C120000;
        mem_array[12] = 32'hFF000000;
        for (i = 13; i < 63; i = i + 1) begin
            mem_array[i] = 32'b0;  // Inicializa todos com zero
        end
    end
    
    always @(*) begin
        // a saída é 0.
        ReadData = 32'h0;
        if (MemRead) begin
            //verifica se o esta dentro dos limites (0,63)
            //se o endreco for maior que 0xFF (255),ele nao ta no espaco
            ReadData = mem_array[word_index];// ve a posicao do array
        end
    end
    //logica de escrita (store - mov [rx], ry)

    always @(posedge clk) begin
        if (MemWrite) begin
            //escreve os dados no indice da palavra selec
            mem_array[word_index] = WriteData;
        end
    end




endmodule

processador/PQP.v
`include "processador/ALU.v"
`include "processador/extensao_sinal.v"
`include "processador/memoria.v"
`include "processador/Registradores.v"
`include "processador/ControlLogicUnit.v"
`include "processador/ALUControl.v"
`include "processador/ShiftLeft2.v"

module PQP(
    input i_Clk,
    input i_Rst
);

    wire [31:0] instrucao;
    wire Jump, MemRead, MemWrite, ALUSrc, RegWrite, RegToReg, Halt;
    wire [1:0] CLU_ALUOp;

    wire [31:0] Reg_ReadData1, Reg_ReadData2, Reg_WriteData;

    wire [31:0] sinalExtendido;
    wire [31:0] ALU_entradaA;
    wire [31:0] ALU_entradaB;
    wire [31:0] Mem_Address;

    wire [3:0] AC_ALUOp;
    wire [31:0] ALUResult;

    wire [31:0] Mem_ReadData;

    wire [31:0] sinalShift;

    reg [31:0] PC;
    wire [31:0] PC_mais4;
    wire [31:0] PC_Jump;
    wire [31:0] proximo_PC;

    always@(posedge i_Clk or posedge i_Rst) begin
        if (i_Rst) begin
            PC <= 32'b0;
        end else begin;
            if (Halt) PC <= PC;
            else PC <= proximo_PC;
        end
    end

    ALU soma_pc(
        .A(PC),
        .B(32'd4),
        .ALUOperation(4'b1001),
        .ALUResult(PC_mais4),
        .Zero()
    );

    assign Mem_Address = (MemRead) ? Reg_ReadData2 : Reg_ReadData1;

    memory memoria(
        .clk(i_Clk),
        .MemWrite(MemWrite),
        .MemRead(MemRead),
        .MemAddress(Mem_Address),
        .WriteData(Reg_ReadData2),
        .ReadData(Mem_ReadData),
        .instructionAddress(PC),
        .instruction(instrucao)
    );

    extensao_sinal extensor(
        .in(instrucao[15:0]),
        .out(sinalExtendido)
    );

    assign Reg_WriteData = (MemRead) ? Mem_ReadData : ALUResult;
    Registradores banco(
        .ReadRegister1(instrucao[23:20]),
        .ReadRegister2(instrucao[19:16]),
        .WriteRegister(instrucao[23:20]),
        .WriteData(Reg_WriteData),
        .RegWrite(RegWrite),
        .clock(i_Clk),
        .ReadData1(Reg_ReadData1),
        .ReadData2(Reg_ReadData2)
    );
    
    ControlLogicUnit clu(
        .Opcode(instrucao[31:24]),
        .Jump(Jump),
        .MemRead(MemRead),
        .ALUOp(CLU_ALUOp),
        .MemWrite(MemWrite),
        .ALUSrc(ALUSrc),
        .RegWrite(RegWrite),
        .RegToReg(RegToReg),
        .Halt(Halt)
    );

    ALUControl aluc(
        .i_ALUOp(CLU_ALUOp),
        .o_Op(AC_ALUOp)
    );
    assign ALU_entradaA = (RegToReg) ? 32'b0 : Reg_ReadData1;
    assign ALU_entradaB = (ALUSrc) ? sinalExtendido : Reg_ReadData2;
    ALU mainALU(
        .A(ALU_entradaA),
        .B(ALU_entradaB),
        .ALUOperation(AC_ALUOp),
        .ALUResult(ALUResult),
        .Zero()
    );

    ShiftLeft2 shift(
        .in(instrucao[15:0]),
        .out(sinalShift)
    );

    assign proximo_PC = (Jump) ? PC_Jump : PC_mais4;
    ALU ALUJump(
        .A(sinalShift),
        .B(PC_mais4),
        .ALUOperation(4'b1001),
        .ALUResult(PC_Jump),
        .Zero()
    );

endmodule

simulacao.v
`timescale 1ns/1ns
`include "processador/PQP.v"


module Simulacao;

    reg clk;
    reg reset;

    PQP pqp(
        .i_Clk(clk),
        .i_Rst(reset)
    );

    // Gera o clock
    always #5 clk = ~clk;

    initial begin
        // Inicializa sinais
        clk = 0;
        reset = 0;  // Desabilita o reset. No comeco, PC desconhecido.
        #5
        reset = 1;
        #10
        reset = 0;
        #150
        $finish;
    end

    // Monitora as instruções buscadas
    always @(posedge clk) begin
        $display("PC: %d | Instrucao: %x | Instrucao jump: %b", pqp.PC, pqp.instrucao, pqp.Jump);
    end
    
    // Bloco para inicializar o dump de formas de onda
    // em um VCD para ver no GTK Wave.
    integer i;
    initial begin
        $dumpfile("sim.vcd"); // Nome do arquivo de saída
        $dumpvars(0, Simulacao);    // Registrar todas as variáveis deste módulo
        for (i=0; i<16; i=i+1) begin
            $dumpvars(1, Simulacao.pqp.banco.registers[i]);
        end
    end

endmodule

sim.vcd
$date
	Fri Nov 07 04:11:47 2025
$end
$version
	Icarus Verilog
$end
$timescale
	1ns
$end
$scope module Simulacao $end
$var reg 1 ! clk $end
$var reg 1 " reset $end
$var integer 32 # i [31:0] $end
$scope module pqp $end
$var wire 1 ! i_Clk $end
$var wire 1 " i_Rst $end
$var wire 32 $ sinalShift [31:0] $end
$var wire 32 % sinalExtendido [31:0] $end
$var wire 32 & proximo_PC [31:0] $end
$var wire 32 ' instrucao [31:0] $end
$var wire 32 ( Reg_WriteData [31:0] $end
$var wire 32 ) Reg_ReadData2 [31:0] $end
$var wire 32 * Reg_ReadData1 [31:0] $end
$var wire 1 + RegWrite $end
$var wire 1 , RegToReg $end
$var wire 32 - PC_mais4 [31:0] $end
$var wire 32 . PC_Jump [31:0] $end
$var wire 32 / Mem_ReadData [31:0] $end
$var wire 32 0 Mem_Address [31:0] $end
$var wire 1 1 MemWrite $end
$var wire 1 2 MemRead $end
$var wire 1 3 Jump $end
$var wire 1 4 Halt $end
$var wire 2 5 CLU_ALUOp [1:0] $end
$var wire 32 6 ALU_entradaB [31:0] $end
$var wire 32 7 ALU_entradaA [31:0] $end
$var wire 1 8 ALUSrc $end
$var wire 32 9 ALUResult [31:0] $end
$var wire 4 : AC_ALUOp [3:0] $end
$var reg 32 ; PC [31:0] $end
$scope module ALUJump $end
$var wire 4 < ALUOperation [3:0] $end
$var wire 1 = Zero $end
$var wire 32 > B [31:0] $end
$var wire 32 ? A [31:0] $end
$var reg 32 @ ALUResult [31:0] $end
$upscope $end
$scope module aluc $end
$var wire 2 A i_ALUOp [1:0] $end
$var reg 4 B o_Op [3:0] $end
$upscope $end
$scope module banco $end
$var wire 32 C ReadData1 [31:0] $end
$var wire 32 D ReadData2 [31:0] $end
$var wire 4 E ReadRegister1 [3:0] $end
$var wire 4 F ReadRegister2 [3:0] $end
$var wire 32 G WriteData [31:0] $end
$var wire 4 H WriteRegister [3:0] $end
$var wire 1 ! clock $end
$var wire 1 + RegWrite $end
$var integer 32 I i [31:0] $end
$upscope $end
$scope module clu $end
$var wire 8 J Opcode [7:0] $end
$var reg 2 K ALUOp [1:0] $end
$var reg 1 8 ALUSrc $end
$var reg 1 4 Halt $end
$var reg 1 3 Jump $end
$var reg 1 2 MemRead $end
$var reg 1 1 MemWrite $end
$var reg 1 , RegToReg $end
$var reg 1 + RegWrite $end
$upscope $end
$scope module extensor $end
$var wire 16 L in [15:0] $end
$var wire 32 M out [31:0] $end
$upscope $end
$scope module mainALU $end
$var wire 32 N A [31:0] $end
$var wire 4 O ALUOperation [3:0] $end
$var wire 32 P B [31:0] $end
$var wire 1 Q Zero $end
$var reg 32 R ALUResult [31:0] $end
$upscope $end
$scope module memoria $end
$var wire 32 S MemAddress [31:0] $end
$var wire 1 2 MemRead $end
$var wire 1 1 MemWrite $end
$var wire 32 T WriteData [31:0] $end
$var wire 1 ! clk $end
$var wire 32 U instruction [31:0] $end
$var wire 32 V instructionAddress [31:0] $end
$var wire 6 W word_index [5:0] $end
$var reg 32 X ReadData [31:0] $end
$var integer 32 Y i [31:0] $end
$upscope $end
$scope module shift $end
$var wire 16 Z in [15:0] $end
$var wire 32 [ out [31:0] $end
$upscope $end
$scope module soma_pc $end
$var wire 32 \ A [31:0] $end
$var wire 4 ] ALUOperation [3:0] $end
$var wire 32 ^ B [31:0] $end
$var wire 1 _ Zero $end
$var reg 32 ` ALUResult [31:0] $end
$upscope $end
$upscope $end
$upscope $end
$scope module Simulacao $end
$scope module pqp $end
$scope module banco $end
$var reg 32 a \registers[0] [31:0] $end
$upscope $end
$upscope $end
$upscope $end
$scope module Simulacao $end
$scope module pqp $end
$scope module banco $end
$var reg 32 b \registers[1] [31:0] $end
$upscope $end
$upscope $end
$upscope $end
$scope module Simulacao $end
$scope module pqp $end
$scope module banco $end
$var reg 32 c \registers[2] [31:0] $end
$upscope $end
$upscope $end
$upscope $end
$scope module Simulacao $end
$scope module pqp $end
$scope module banco $end
$var reg 32 d \registers[3] [31:0] $end
$upscope $end
$upscope $end
$upscope $end
$scope module Simulacao $end
$scope module pqp $end
$scope module banco $end
$var reg 32 e \registers[4] [31:0] $end
$upscope $end
$upscope $end
$upscope $end
$scope module Simulacao $end
$scope module pqp $end
$scope module banco $end
$var reg 32 f \registers[5] [31:0] $end
$upscope $end
$upscope $end
$upscope $end
$scope module Simulacao $end
$scope module pqp $end
$scope module banco $end
$var reg 32 g \registers[6] [31:0] $end
$upscope $end
$upscope $end
$upscope $end
$scope module Simulacao $end
$scope module pqp $end
$scope module banco $end
$var reg 32 h \registers[7] [31:0] $end
$upscope $end
$upscope $end
$upscope $end
$scope module Simulacao $end
$scope module pqp $end
$scope module banco $end
$var reg 32 i \registers[8] [31:0] $end
$upscope $end
$upscope $end
$upscope $end
$scope module Simulacao $end
$scope module pqp $end
$scope module banco $end
$var reg 32 j \registers[9] [31:0] $end
$upscope $end
$upscope $end
$upscope $end
$scope module Simulacao $end
$scope module pqp $end
$scope module banco $end
$var reg 32 k \registers[10] [31:0] $end
$upscope $end
$upscope $end
$upscope $end
$scope module Simulacao $end
$scope module pqp $end
$scope module banco $end
$var reg 32 l \registers[11] [31:0] $end
$upscope $end
$upscope $end
$upscope $end
$scope module Simulacao $end
$scope module pqp $end
$scope module banco $end
$var reg 32 m \registers[12] [31:0] $end
$upscope $end
$upscope $end
$upscope $end
$scope module Simulacao $end
$scope module pqp $end
$scope module banco $end
$var reg 32 n \registers[13] [31:0] $end
$upscope $end
$upscope $end
$upscope $end
$scope module Simulacao $end
$scope module pqp $end
$scope module banco $end
$var reg 32 o \registers[14] [31:0] $end
$upscope $end
$upscope $end
$upscope $end
$scope module Simulacao $end
$scope module pqp $end
$scope module banco $end
$var reg 32 p \registers[15] [31:0] $end
$upscope $end
$upscope $end
$upscope $end
$enddefinitions $end
$comment Show the parameter values. $end
$dumpall
$end
#0
$dumpvars
b0 p
b0 o
b0 n
b0 m
b0 l
b0 k
b0 j
b0 i
b0 h
b0 g
b0 f
b0 e
b0 d
b0 c
b0 b
b0 a
bx `
x_
b100 ^
b1001 ]
bx \
b0xxxxxxxxxxxxxx00 [
bx Z
b111111 Y
b0 X
bx W
bx V
bx U
bx T
bx S
bx R
xQ
bx P
bx O
bx N
bx M
bx L
bx K
bx J
b10000 I
bx H
bx G
bx F
bx E
bx D
bx C
bx B
bx A
bx @
b0xxxxxxxxxxxxxx00 ?
bx >
x=
b1001 <
bx ;
bx :
bx 9
x8
bx 7
bx 6
bx 5
x4
x3
x2
x1
bx 0
b0 /
bx .
bx -
x,
x+
bx *
bx )
bx (
bx '
bx &
bx %
b0xxxxxxxxxxxxxx00 $
b10000 #
0"
0!
$end
#5
0=
0Q
b100000100 .
b100000100 @
b1001 :
b1001 B
b1001 O
b1000000 (
b1000000 G
b100 &
b0 W
b1000000 9
b1000000 R
b100000000 $
b100000000 ?
b100000000 [
04
0,
1+
18
01
b10 5
b10 A
b10 K
02
03
b0 7
b0 N
b0 0
b0 S
b1000000 6
b1000000 P
b1000000 Z
b0 J
b1 H
b0 )
b0 D
b0 T
b0 F
b0 *
b0 C
b1 E
b1000000 %
b1000000 M
b1000000 L
0_
b100000000000001000000 '
b100000000000001000000 U
b100 -
b100 >
b100 `
b0 ;
b0 V
b0 \
1"
1!
#10
0!
#15
0Q
b1000000 (
b1000000 G
b0 $
b0 ?
b0 [
1,
08
b1000000 6
b1000000 P
b1000000 9
b1000000 R
b0 W
b0 Z
b1 J
b10 H
b1000000 )
b1000000 D
b1000000 T
b1 F
b10 E
b0 %
b0 M
b0 L
b1000 &
b1000 .
b1000 @
b0 7
b0 N
b0 0
b0 S
b1001000010000000000000000 '
b1001000010000000000000000 U
b1000 -
b1000 >
b1000 `
b1000000 b
b0 *
b0 C
b100 ;
b100 V
b100 \
1!
0"
#20
0!
#25
b1000000 7
b1000000 N
b1011 :
b1011 B
b1011 O
0,
0+
11
b0 5
b0 A
b0 K
b10000 W
b11 J
b1100 &
b1100 .
b1100 @
b1000000 0
b1000000 S
b11001000010000000000000000 '
b11001000010000000000000000 U
b1100 -
b1100 >
b1100 `
b1000000 c
b1000000 *
b1000000 C
b1000 ;
b1000 V
b1000 \
1!
#30
0!
#35
0Q
b1001 :
b1001 B
b1001 O
b1000000 /
b1000000 X
b1000000 (
b1000000 G
b1000000 9
b1000000 R
b10000 W
1+
01
b10 5
b10 A
b10 K
12
b0 7
b0 N
b1000000 0
b1000000 S
b10 J
b11 H
b10 F
b0 *
b0 C
b11 E
b10000 &
b10000 .
b10000 @
b10001100100000000000000000 '
b10001100100000000000000000 U
b10000 -
b10000 >
b10000 `
b1100 ;
b1100 V
b1100 \
1!
#40
0!
#45
0Q
b0 /
b0 X
b11 (
b11 G
b0 W
b1100 $
b1100 ?
b1100 [
0+
18
02
13
b11 6
b11 P
b0 0
b0 S
b11 9
b11 R
b11 Z
b101 J
b0 H
b0 )
b0 D
b0 T
b0 F
b0 E
b11 %
b11 M
b11 L
b100000 &
b100000 .
b100000 @
b0 7
b0 N
b101000000000000000000000011 '
b101000000000000000000000011 U
b10100 -
b10100 >
b10100 `
b1000000 d
b0 *
b0 C
b10000 ;
b10000 V
b10000 \
1!
#50
0!
#55
b10000000 (
b10000000 G
b10000 W
b10000000 9
b10000000 R
b0 $
b0 ?
b0 [
1+
08
03
b1000000 7
b1000000 N
b1000000 0
b1000000 S
b1000000 6
b1000000 P
b100100 &
b0 Z
b1001 J
b1 H
b1000000 )
b1000000 D
b1000000 T
b10 F
b1000000 *
b1000000 C
b1 E
b0 %
b0 M
b0 L
b100100 .
b100100 @
b1001000100100000000000000000 '
b1001000100100000000000000000 U
b100100 -
b100100 >
b100100 `
b100000 ;
b100000 V
b100000 \
1!
#60
0!
#65
b1010 :
b1010 B
b1010 O
b1000000 (
b1000000 G
b11 5
b11 A
b11 K
b1000000 9
b1000000 R
b100000 W
b1010 J
b101000 &
b101000 .
b101000 @
b10000000 7
b10000000 N
b10000000 0
b10000000 S
b1010000100100000000000000000 '
b1010000100100000000000000000 U
b101000 -
b101000 >
b101000 `
b10000000 b
b10000000 *
b10000000 C
b100100 ;
b100100 V
b100100 \
1!
#70
0!
#75
b1011 :
b1011 B
b1011 O
1Q
b0 (
b0 G
b0 5
b0 A
b0 K
b0 6
b0 P
b0 9
b0 R
b10000 W
b1011 J
b0 )
b0 D
b0 T
b100 F
b101100 &
b101100 .
b101100 @
b1000000 7
b1000000 N
b1000000 0
b1000000 S
b1011000101000000000000000000 '
b1011000101000000000000000000 U
b101100 -
b101100 >
b101100 `
b1000000 b
b1000000 *
b1000000 C
b101000 ;
b101000 V
b101000 \
1!
#80
0!
#85
0Q
b1000000 (
b1000000 G
b1000000 9
b1000000 R
b1100 :
b1100 B
b1100 O
b1 5
b1 A
b1 K
b1000000 6
b1000000 P
b0 W
b1100 J
b1000000 )
b1000000 D
b1000000 T
b10 F
b110000 &
b110000 .
b110000 @
b0 7
b0 N
b0 0
b0 S
b1100000100100000000000000000 '
b1100000100100000000000000000 U
b110000 -
b110000 >
b110000 `
b0 b
b0 *
b0 C
b101100 ;
b101100 V
b101100 \
1!
#90
0!
#95
1Q
b0 (
b0 G
b1011 :
b1011 B
b1011 O
b0 9
b0 R
14
0+
b0 5
b0 A
b0 K
b0 6
b0 P
b0 W
b11111111 J
b0 H
b0 )
b0 D
b0 T
b0 F
b0 E
b110100 &
b110100 .
b110100 @
b0 7
b0 N
b0 0
b0 S
b11111111000000000000000000000000 '
b11111111000000000000000000000000 U
b110100 -
b110100 >
b110100 `
b1000000 b
b0 *
b0 C
b110000 ;
b110000 V
b110000 \
1!
